flylog/__init__.py
flylog/constants.py
flylog/api/__init__.py
flylog/api/client.py
flylog/api/log_handler.py
flylog/server/__init__.py
flylog/server/log.py
flylog/server/redis_helper.py
flylog/server/server.py
flylog/server/six.py
flylog/server/utils.py
flylog/server/backends/__init__.py
flylog/server/backends/ding.py
flylog/server/backends/mail.py
flylog/server/backends/robot.py
flylog/server/backends/send_slack.py
flylog/server/backends/sendcloud.py
flylog_extra-3.0.9.data/scripts/run_flylog.py
flylog_extra-3.0.9.dist-info/METADATA
flylog_extra-3.0.9.dist-info/WHEEL
flylog_extra-3.0.9.dist-info/top_level.txt
flylog_extra-3.0.9.dist-info/RECORD
