Metadata-Version: 2.1
Name: flylog-extra
Version: 3.0.9
Summary: make log fly to mail or other(slack)
Home-page: https://github.com/dkxx00/flylog
Author: dkxx00
Author-email: hymanxx6@gmail.com
License: BSD
Platform: any
